{
  "3.1 phillip lim": {
    "last_failed": "2026-05-05T09:49:22.042308+00:00"
  },
  "a.emery": {
    "last_failed": "2026-05-05T10:42:41.531836+00:00"
  },
  "adam lippes": {
    "last_failed": "2026-05-05T09:49:22.042313+00:00"
  },
  "akris": {
    "last_failed": "2026-05-05T10:42:41.531850+00:00"
  },
  "akris punto": {
    "last_failed": "2026-05-05T10:42:41.532037+00:00"
  },
  "alice + olivia": {
    "last_failed": "2026-05-05T09:49:22.042248+00:00"
  },
  "altuzarra": {
    "last_failed": "2026-05-05T10:42:41.531771+00:00"
  },
  "another tomorrow": {
    "last_failed": "2026-05-05T10:53:19.708325+00:00"
  },
  "asics": {
    "last_failed": "2026-05-05T09:40:23.592914+00:00"
  },
  "autumn cashmere": {
    "last_failed": "2026-05-05T10:53:19.708221+00:00"
  },
  "badgley mischka": {
    "last_failed": "2026-05-05T09:40:23.593072+00:00"
  },
  "bernardo": {
    "last_failed": "2026-05-05T10:42:41.531990+00:00"
  },
  "brandon maxwell": {
    "last_failed": "2026-05-05T10:42:41.531828+00:00"
  },
  "cami nyc": {
    "last_failed": "2026-05-05T09:40:23.593086+00:00"
  },
  "colorush": {
    "last_failed": "2026-05-05T09:40:23.593068+00:00"
  },
  "cynthia rowley": {
    "last_failed": "2026-05-05T10:42:41.531966+00:00"
  },
  "fabiana filippi": {
    "last_failed": "2026-05-05T09:49:22.042389+00:00"
  },
  "fancy feast": {
    "last_failed": "2026-05-10T16:58:54.012026+00:00"
  },
  "friskies": {
    "last_failed": "2026-05-10T16:58:54.012070+00:00"
  },
  "gabriela hearst": {
    "last_failed": "2026-05-05T09:40:23.593050+00:00"
  },
  "golden goose": {
    "last_failed": "2026-05-05T10:42:41.531820+00:00"
  },
  "guest in residence": {
    "last_failed": "2026-05-07T13:28:18.409975+00:00"
  },
  "heirlome": {
    "last_failed": "2026-05-05T10:42:41.531803+00:00"
  },
  "joe's jeans": {
    "last_failed": "2026-05-05T10:42:41.531812+00:00"
  },
  "jw anderson": {
    "last_failed": "2026-05-05T10:53:19.708341+00:00"
  },
  "l'agence": {
    "last_failed": "2026-05-05T09:49:22.042365+00:00"
  },
  "loro piana": {
    "last_failed": "2026-05-05T09:40:23.593108+00:00"
  },
  "marni": {
    "last_failed": "2026-05-05T09:40:23.593104+00:00"
  },
  "max mara": {
    "last_failed": "2026-05-05T10:53:19.708378+00:00"
  },
  "minnie rose": {
    "last_failed": "2026-05-05T10:53:19.708346+00:00"
  },
  "mm6 maison margiela": {
    "last_failed": "2026-05-05T09:40:23.593090+00:00"
  },
  "moon boot": {
    "last_failed": "2026-05-05T09:49:22.042293+00:00"
  },
  "naadam": {
    "last_failed": "2026-05-05T09:40:23.593123+00:00"
  },
  "naghedi": {
    "last_failed": "2026-05-05T10:53:19.708374+00:00"
  },
  "odiss\u00ec": {
    "last_failed": "2026-05-05T10:42:41.531832+00:00"
  },
  "pierre hardy": {
    "last_failed": "2026-05-05T10:42:41.531845+00:00"
  },
  "purina one": {
    "last_failed": "2026-05-10T16:58:54.012055+00:00"
  },
  "purina pro plan": {
    "last_failed": "2026-05-10T16:58:54.012060+00:00"
  },
  "purina pro plan veterinary diets": {
    "last_failed": "2026-05-10T16:58:54.012065+00:00"
  },
  "ramy brook": {
    "last_failed": "2026-05-05T09:49:22.042369+00:00"
  },
  "reiss atelier": {
    "last_failed": "2026-05-05T09:49:22.042325+00:00"
  },
  "santoni": {
    "last_failed": "2026-05-05T10:53:19.708262+00:00"
  },
  "schutz": {
    "last_failed": "2026-05-05T10:42:41.531815+00:00"
  },
  "sprwmn": {
    "last_failed": "2026-05-05T10:53:19.708382+00:00"
  },
  "staud": {
    "last_failed": "2026-05-05T09:49:22.042321+00:00"
  },
  "stellae dux": {
    "last_failed": "2026-05-05T09:49:22.042317+00:00"
  },
  "stuart weitzman": {
    "last_failed": "2026-05-05T09:49:22.042385+00:00"
  },
  "tanya taylor": {
    "last_failed": "2026-05-05T09:49:22.042349+00:00"
  },
  "teri jon by rickie freeman": {
    "last_failed": "2026-05-05T09:40:23.593112+00:00"
  },
  "tiki cat": {
    "last_failed": "2026-05-07T21:43:07.441080+00:00"
  },
  "tod's": {
    "last_failed": "2026-05-05T10:53:19.708126+00:00"
  },
  "toteme": {
    "last_failed": "2026-05-05T09:40:23.593046+00:00"
  },
  "twp": {
    "last_failed": "2026-05-05T09:49:22.042374+00:00"
  },
  "ulla johnson": {
    "last_failed": "2026-05-05T09:49:22.042382+00:00"
  },
  "veronica beard": {
    "last_failed": "2026-05-05T09:49:22.042377+00:00"
  },
  "weekend max mara": {
    "last_failed": "2026-05-05T10:42:41.531840+00:00"
  }
}
