{
  "mcpServers": {
    "veraStudioArchive": {
      "title": "Vera · Archivio dello Studio",
      "description": "Configure, refresh, search, and verify a private local archive index, plus plan and validate client-scoped Gmail retrieval without storing mailbox credentials or content.",
      "icons": [
        {
          "src": "./assets/icon.svg",
          "mimeType": "image/svg+xml",
          "sizes": ["24x24"]
        }
      ],
      "cwd": ".",
      "command": "node",
      "args": ["./mcp/server.cjs", "--stdio"]
    }
  }
}
